README.md
setup.py
jeeachinto/__init__.py
jeeachinto/client.py
jeeachinto/server.py
jeeachinto/universal_lock.py
jeeachinto/utils.py
jeeachinto.egg-info/PKG-INFO
jeeachinto.egg-info/SOURCES.txt
jeeachinto.egg-info/dependency_links.txt
jeeachinto.egg-info/requires.txt
jeeachinto.egg-info/top_level.txt