Metadata-Version: 2.1
Name: jeeachinto
Version: 0.3.5
Summary: Connect to hosts in an easier way
Home-page: https://github.com/naodellerba/jeeachinto
Author: IISS Luigi Dell' Erba
Author-email: naoittdellerba@gmail.com
License: UNKNOWN
Platform: UNKNOWN
Classifier: License :: OSI Approved :: MIT License
Requires-Python: >=2.7
